gb_projects_pages/__init__.py
gb_projects_pages/projects_pages.py
gb_projects_pages-1.0.4.dist-info/entry_points.txt
gb_projects_pages-1.0.4.dist-info/WHEEL
gb_projects_pages-1.0.4.dist-info/METADATA
gb_projects_pages-1.0.4.dist-info/RECORD
