Metadata-Version: 2.1
Name: gb-projects-pages
Version: 1.0.4
Summary: CLI command for updating the Ensembl projects pages
License: Apache-2.0
Author: leannehaggerty
Author-email: leannehaggerty@gmail.com
Requires-Python: >=3.8,<4.0
Classifier: License :: OSI Approved :: Apache Software License
Classifier: Programming Language :: Python :: 3
Classifier: Programming Language :: Python :: 3.8
Classifier: Programming Language :: Python :: 3.9
Classifier: Programming Language :: Python :: 3.10
Requires-Dist: PyMySQL (>=0.10.1,<0.11.0)
Requires-Dist: mysql-connector (>=2.2.9,<3.0.0)
Requires-Dist: mysql-connector-python (>=8.0.22,<9.0.0)
Requires-Dist: pysftp (>=0.2.9,<0.3.0)
Requires-Dist: requests (>=2.25.0,<3.0.0)
